booking_extension/__init__.py
booking_extension/_version.py
booking_extension/handlers.py
booking_extension-0.1.0.data/data/etc/jupyter/jupyter_server_config.d/booking_extension.json
booking_extension-0.1.0.data/data/share/jupyter/labextensions/booking_extension/build_log.json
booking_extension-0.1.0.data/data/share/jupyter/labextensions/booking_extension/package.json
booking_extension-0.1.0.data/data/share/jupyter/labextensions/booking_extension/schemas/booking_extension/package.json.orig
booking_extension-0.1.0.data/data/share/jupyter/labextensions/booking_extension/schemas/booking_extension/plugin.json
booking_extension-0.1.0.data/data/share/jupyter/labextensions/booking_extension/static/lib_index_js.e52dcac7bac22ffc2fa5.js
booking_extension-0.1.0.data/data/share/jupyter/labextensions/booking_extension/static/lib_index_js.e52dcac7bac22ffc2fa5.js.map
booking_extension-0.1.0.data/data/share/jupyter/labextensions/booking_extension/static/remoteEntry.f7b0f393efe5e88c24df.js
booking_extension-0.1.0.data/data/share/jupyter/labextensions/booking_extension/static/remoteEntry.f7b0f393efe5e88c24df.js.map
booking_extension-0.1.0.data/data/share/jupyter/labextensions/booking_extension/static/style.js
booking_extension-0.1.0.data/data/share/jupyter/labextensions/booking_extension/static/style_index_js.0ad7f18b8985d45a3052.js
booking_extension-0.1.0.data/data/share/jupyter/labextensions/booking_extension/static/style_index_js.0ad7f18b8985d45a3052.js.map
booking_extension-0.1.0.data/data/share/jupyter/labextensions/booking_extension/install.json
booking_extension-0.1.0.dist-info/METADATA
booking_extension-0.1.0.dist-info/WHEEL
booking_extension-0.1.0.dist-info/licenses/LICENSE
booking_extension-0.1.0.dist-info/RECORD
